einshard/__init__.py
einshard/einshard.py
einshard/parser.py
einshard/parsec/Either.py
einshard/parsec/Void.py
einshard/parsec/__init__.py
einshard/parsec/parsec.py
einshard-0.2.0.dist-info/LICENSE
einshard-0.2.0.dist-info/METADATA
einshard-0.2.0.dist-info/WHEEL
einshard-0.2.0.dist-info/top_level.txt
einshard-0.2.0.dist-info/RECORD
