Metadata-Version: 2.1
Name: einshard
Version: 0.2.0
Summary: High-level array sharding API for JAX
Author-email: Ayaka <ayaka@mail.shn.hk>, Shin <shin@yixiaoer.sg>
Project-URL: Homepage, https://github.com/ayaka14732/einshard
Project-URL: Issues, https://github.com/ayaka14732/einshard/issues
Classifier: Programming Language :: Python :: 3
Classifier: License :: CC0 1.0 Universal (CC0 1.0) Public Domain Dedication
Classifier: Topic :: System :: Distributed Computing
Classifier: Operating System :: OS Independent
Requires-Python: >=3.12
License-File: LICENSE
Requires-Dist: jax
Requires-Dist: mypy
